blcutools/__init__.py
blcutools/nlp/__init__.py
blcutools/nlp/preprocess/__init__.py
blcutools/nlp/preprocess/split_sentence_with_puncs.py
blcutools-0.0.0b0.dist-info/LICENSE
blcutools-0.0.0b0.dist-info/METADATA
blcutools-0.0.0b0.dist-info/WHEEL
blcutools-0.0.0b0.dist-info/top_level.txt
blcutools-0.0.0b0.dist-info/RECORD
