Metadata-Version: 2.1
Name: blcutools
Version: 0.0.0b0
Summary: blcutools
Home-page: https://github.com/blcu-research/blcutools
Author: blcuresearch
Author-email: blcures@gmail.com
License: UNKNOWN
Project-URL: Bug Tracker, https://github.com/blcu-research/blcutools/issues
Platform: UNKNOWN
Classifier: Programming Language :: Python :: 3
Classifier: License :: OSI Approved :: Apache Software License
Classifier: Operating System :: OS Independent
Requires-Python: >=3.6
License-File: LICENSE
